{
  "draw": 1,
  "recordsTotal": 23,
  "recordsFiltered": 23,
  "data": [
    {
      "id": 1,
      "user": "某人",
      "userLevel": "爱心天使",
      "goods": "帅风立式净水器",
      "methodCode": 0,
      "orderId": "20164100145",
      "orderUser": "老常A",
      "phone": 15677776666,
      "category": "饮水机",
      "type": "u56 立式",
      "amount": 3999,
      "package": "一月时长套餐",
      "method": "全款",
      "total": 5000.00,
      "address": "阡陌路482号智慧E谷B栋",
      "status": "待付款",
      "statusCode": 0,
      "orderTime": "2999-11-11",
      "quickDoneAble": true
    },
    {
      "id": 2,
      "user": "某人",
      "userLevel": "爱心天使",
      "goods": "帅风立式净水器",
      "methodCode": 0,
      "orderId": "20164100145",
      "orderUser": "李菲菲",
      "phone": 15677776666,
      "category": "饮水机",
      "type": "u59 立式",
      "amount": 4858,
      "package": "一月时长套餐",
      "method": "全款",
      "total": 5000.00,
      "address": "阡陌路482号智慧E谷B栋",
      "status": "待付款",
      "statusCode": 1,
      "orderTime": "2999-11-11",
      "quickDoneAble": false
    },
    {
      "id": 3,
      "user": "某人",
      "userLevel": "爱心天使",
      "goods": "帅风立式净水器",
      "methodCode": 0,
      "orderId": "20164100145",
      "orderUser": "呵呵~",
      "phone": 15677776666,
      "category": "饮水机",
      "type": "u56 立式",
      "amount": 7881,
      "package": "一月时长套餐",
      "method": "全款",
      "total": 5000.00,
      "address": "阡陌路482号智慧E谷B栋",
      "status": "待收货",
      "orderTime": "2999-11-11",
      "quickDoneAble": false
    },
    {
      "id": 4,
      "user": "某人",
      "userLevel": "爱心天使",
      "goods": "帅风立式净水器",
      "methodCode": 0,
      "orderId": "20164100145",
      "orderUser": "maybe",
      "phone": 15677776666,
      "category": "饮水机",
      "type": "u56 立式",
      "amount": 123,
      "package": "一月时长套餐",
      "method": "全款",
      "total": 5000.00,
      "address": "阡陌路482号智慧E谷B栋",
      "status": "未发货",
      "orderTime": "2999-11-11",
      "quickDoneAble": false
    },
    {
      "id": 5,
      "user": "某人",
      "userLevel": "爱心天使",
      "goods": "帅风立式净水器",
      "methodCode": 0,
      "orderId": "20164100145",
      "orderUser": "在家",
      "phone": 15677776666,
      "category": "饮水机",
      "type": "u56 立式",
      "amount": 789,
      "package": "一月时长套餐",
      "method": "全款",
      "total": 5000.00,
      "address": "阡陌路482号智慧E谷B栋",
      "status": "未安装",
      "orderTime": "2999-11-11",
      "quickDoneAble": false
    },
    {
      "id": 6,
      "user": "某人",
      "userLevel": "爱心天使",
      "goods": "帅风立式净水器",
      "methodCode": 0,
      "orderId": "20164100145",
      "orderUser": "放假哦发生的",
      "phone": 15677776666,
      "category": "饮水机",
      "type": "u56 立式",
      "amount": 456,
      "package": "一月时长套餐",
      "method": "全款",
      "total": 5000.00,
      "address": "阡陌路482号智慧E谷B栋",
      "status": "已安装",
      "orderTime": "2999-11-11",
      "quickDoneAble": false
    },
    {
      "id": 6,
      "user": "某人",
      "userLevel": "爱心天使",
      "goods": "帅风立式净水器",
      "methodCode": 0,
      "orderId": "20164100145",
      "orderUser": "放假哦发生的",
      "phone": 15677776666,
      "category": "饮水机",
      "type": "u56 立式",
      "amount": 456,
      "package": "一月时长套餐",
      "method": "全款",
      "total": 5000.00,
      "address": "阡陌路482号智慧E谷B栋",
      "status": "待派单",
      "statusCode": 6,
      "orderTime": "2999-11-11",
      "quickDoneAble": false
    }
  ]
}